[
  {
    "name": "contact",
    "path": "/contact",
    "component": "C:\\\\Users\\\\Cob\\\\Documents\\\\GitHub\\\\jacobsmith2023\\\\pages\\\\contact.vue",
    "chunkName": "pages/contact",
    "_name": "_37c0ec52"
  },
  {
    "name": "resume",
    "path": "/resume",
    "component": "C:\\\\Users\\\\Cob\\\\Documents\\\\GitHub\\\\jacobsmith2023\\\\pages\\\\resume.vue",
    "chunkName": "pages/resume",
    "_name": "_30557946"
  },
  {
    "name": "index",
    "path": "/",
    "component": "C:\\\\Users\\\\Cob\\\\Documents\\\\GitHub\\\\jacobsmith2023\\\\pages\\\\index.vue",
    "chunkName": "pages/index",
    "_name": "_5ed22149"
  }
]
